<?xml version="1.0"?>
<release version="5.3.12">
  <version>5.3.12</version>
  <date>2012-05-03</date>
  <stage>stable</stage>
  <source>
    <file compression="tar.bz2">
      <name>PHP 5.3.12 (tar.bz2)</name>
      <filename>php-5.3.12.tar.bz2</filename>
      <date>2012-05-03</date>
      <md5>cf02c29be279c506cbd4ffc2819d7c82</md5>
    </file>
    <file compression="tar.gz">
      <name>PHP 5.3.12 (tar.gz)</name>
      <filename>php-5.3.12.tar.gz</filename>
      <date>2012-05-03</date>
      <md5>aac80e478eb0785c50855ae8cefe735a</md5>
    </file>
  </source>
  <announcements>
    <announcement lang="en"/>
  </announcements>
  <changes>
    <modules/>
  </changes>
  <windows_builds/>
  <tags/>
</release>
